COPYING
MANIFEST.in
README.rst
setup.py
cmsplugin_poll/__init__.py
cmsplugin_poll/admin.py
cmsplugin_poll/cms_plugins.py
cmsplugin_poll/models.py
cmsplugin_poll/tests.py
cmsplugin_poll/urls.py
cmsplugin_poll/views.py
cmsplugin_poll.egg-info/PKG-INFO
cmsplugin_poll.egg-info/SOURCES.txt
cmsplugin_poll.egg-info/dependency_links.txt
cmsplugin_poll.egg-info/requires.txt
cmsplugin_poll.egg-info/top_level.txt
cmsplugin_poll/locale/de/LC_MESSAGES/django.mo
cmsplugin_poll/locale/de/LC_MESSAGES/django.po
cmsplugin_poll/locale/fr/LC_MESSAGES/django.mo
cmsplugin_poll/locale/fr/LC_MESSAGES/django.po
cmsplugin_poll/locale/nb/LC_MESSAGES/django.mo
cmsplugin_poll/locale/nb/LC_MESSAGES/django.po
cmsplugin_poll/migrations/0001_initial.py
cmsplugin_poll/migrations/0002_auto__add_field_poll_close_date.py
cmsplugin_poll/migrations/__init__.py
cmsplugin_poll/templates/cmsplugin_poll/detail.html
cmsplugin_poll/templates/cmsplugin_poll/latest_polls.html
cmsplugin_poll/templates/cmsplugin_poll/results.html
cmsplugin_poll/templatetags/__init__.py
cmsplugin_poll/templatetags/poll_tags.py